detect_wizard_src/Actionable.py
detect_wizard_src/Configuration.py
detect_wizard_src/PathTree.py
detect_wizard_src/TarExaminer.py
detect_wizard_src/WizardLogger.py
detect_wizard_src/__init__.py
detect_wizard_src/detect_wizard.py
detect_wizard_src/file_size_util.py
detect_wizard-1.0b27.dist-info/LICENSE
detect_wizard-1.0b27.dist-info/METADATA
detect_wizard-1.0b27.dist-info/WHEEL
detect_wizard-1.0b27.dist-info/entry_points.txt
detect_wizard-1.0b27.dist-info/top_level.txt
detect_wizard-1.0b27.dist-info/RECORD
