Metadata-Version: 2.1
Name: detect-wizard
Version: 1.0b27
Summary: Black Duck scanning wizard to pre-scan folders, determine optimal scan configuration and call Synopsys Detect to scan
Home-page: https://github.com/matthewb66/detect-wizard
Author: Matthew Brady, Jay Ricco, Jaclyn Kaplan, Damon Weinstein
Author-email: w3matt@gmail.com
License: UNKNOWN
Platform: UNKNOWN
Classifier: Programming Language :: Python :: 3
Classifier: License :: OSI Approved :: MIT License
Classifier: Operating System :: OS Independent
Requires-Python: >=3.8
Requires-Dist: libmagic
Requires-Dist: python-magic (>=0.4.15)
Requires-Dist: blackduck (>=0.0.55)
Requires-Dist: texttable (>=1.4.0)
Requires-Dist: python-magic-bin (>=0.4.14) ; platform_system == "Windows"
